{
  "version": "1.0",
  "label": "s3://%s3_bucket%/%state_key%",
  "type": "TERRAFORM-STATE",
  "autoExpand": false,
  "skipEveryInstanceFiles": false,
  "limitToAllowedChildren": false,
  "autoGenerate": false,
  "key": "TERRAFORM-S3-STATE",
  "infoHtml": "",
  "attributes": [
    {
      "name": "aws_region",
      "caption": "AWS region",
      "type": "java.lang.String",
      "formColumn": 1,
      "formOrder": 1300,
      "visibility": "ALWAYS VISIBLE",
      "writability": "ALWAYS",
      "required": true,
      "isPartOfKey": false,
      "listOfValues": "$instance.parent.getAttribute(\"aws_region\")\u003dInherit from parent,us-east-1,eu-west-1",
      "newItemsAllowed": true,
      "parseWithVelocity": true,
      "cloneAttribute": true,
      "autoExport": true,
      "inputPrompt": "",
      "tooltip": "",
      "scope": "Instance",
      "defaultValue": "$instance.parent.getAttribute(\"aws_region\")"
    },
    {
      "name": "encrypt_state_file",
      "caption": "Encrypt",
      "type": "java.lang.Boolean",
      "formColumn": 1,
      "formOrder": 1400,
      "visibility": "ALWAYS VISIBLE",
      "writability": "ALWAYS",
      "required": true,
      "isPartOfKey": false,
      "listOfValues": "",
      "newItemsAllowed": false,
      "parseWithVelocity": false,
      "cloneAttribute": true,
      "autoExport": true,
      "inputPrompt": "",
      "tooltip": "\u003cp\u003eSelect this box if the state should be stored in encrypted format\u003c/p\u003e",
      "scope": "Instance",
      "defaultValue": "0"
    },
    {
      "name": "profile",
      "caption": "Profile",
      "type": "java.lang.String",
      "formColumn": 2,
      "formOrder": 2100,
      "visibility": "ALWAYS VISIBLE",
      "writability": "ALWAYS",
      "required": false,
      "isPartOfKey": false,
      "listOfValues": "",
      "newItemsAllowed": false,
      "parseWithVelocity": false,
      "cloneAttribute": true,
      "autoExport": true,
      "inputPrompt": "",
      "tooltip": "\u003cp\u003eSpecify a profile name if other credentials then those from the AWS core variables should be used.\u003c/p\u003e\n\u003cp\u003eAWS credentials- and config-files are generated before scripts run. A file for both is created with by concatenating all Variables of types AWS-CREDENTIALS and AWS-CONFIG respectively.\u003c/p\u003e",
      "scope": "Instance",
      "defaultValue": ""
    },
    {
      "name": "s3_bucket",
      "caption": "Bucket",
      "type": "java.lang.String",
      "formColumn": 1,
      "formOrder": 1100,
      "visibility": "ALWAYS VISIBLE",
      "writability": "ALWAYS",
      "required": true,
      "isPartOfKey": true,
      "listOfValues": "",
      "newItemsAllowed": false,
      "parseWithVelocity": true,
      "cloneAttribute": true,
      "autoExport": true,
      "inputPrompt": "",
      "tooltip": "",
      "scope": "Instance",
      "defaultValue": ""
    },
    {
      "name": "state_key",
      "caption": "State key",
      "type": "java.lang.String",
      "formColumn": 1,
      "formOrder": 1200,
      "visibility": "ALWAYS VISIBLE",
      "writability": "ALWAYS",
      "required": true,
      "isPartOfKey": true,
      "listOfValues": "",
      "newItemsAllowed": false,
      "parseWithVelocity": true,
      "cloneAttribute": true,
      "autoExport": true,
      "inputPrompt": "",
      "tooltip": "\u003cp\u003eSpecify the path under which state files should be stored.\u003c/p\u003e",
      "scope": "Instance",
      "defaultValue": "dev-environments/env1"
    },
    {
      "name": "state_name",
      "caption": "State name",
      "type": "java.lang.String",
      "formColumn": 1,
      "formOrder": 1000,
      "visibility": "ALWAYS VISIBLE",
      "writability": "ALWAYS",
      "required": true,
      "isPartOfKey": true,
      "listOfValues": "",
      "newItemsAllowed": false,
      "parseWithVelocity": false,
      "cloneAttribute": true,
      "autoExport": true,
      "inputPrompt": "",
      "tooltip": "\u003cp\u003eEnter a name for the state instance. This name can then be used by instance that use this state.\u003c/p\u003e",
      "scope": "Instance",
      "defaultValue": ""
    }
  ],
  "files": [
    {
      "filename": "remote_state.tf",
      "includeName": "",
      "menuCaption": "remote_state.tf",
      "directory": "",
      "runsIndependent": false,
      "runsParallel": false,
      "runBeforeIndependentActions": false,
      "parseWithVelocity": true,
      "executable": false,
      "saveWith": "CURRENT INSTANCE",
      "isInteractive": false,
      "hideRunnerWindow": false,
      "installPipeline": 0,
      "deploymentPipeline": 0,
      "removePipeline": 0,
      "importPipeline": 0,
      "timeoutSeconds": 3600,
      "key": "",
      "menuOrder": 100,
      "menuSeparatorBefore": false,
      "hideFromInstanceActionsMenu": false,
      "hideFromBottomMenu": false,
      "menuPath": ""
    }
  ],
  "allowedChildren": []
}